[
  {
    "id": "module:@the-/driver-mongo",
    "longname": "module:@the-/driver-mongo",
    "name": "@the-/driver-mongo",
    "kind": "module",
    "description": "Mongo driver for the-db",
    "version": "15.4.4",
    "license": "MIT",
    "typicalname": "driverMongo",
    "meta": {
      "lineno": 2,
      "filename": "index.js",
      "path": "/Users/okuni/Projects/the/packages/driver-mongo/lib"
    },
    "order": 1
  },
  {
    "id": "module:@the-/driver-mongo.MongoDriver()",
    "longname": "module:@the-/driver-mongo.MongoDriver",
    "name": "MongoDriver",
    "kind": "constructor",
    "description": "Driver for mongo db",
    "memberof": "module:@the-/driver-mongo.MongoDriver",
    "order": 3
  },
  {
    "id": "module:@the-/driver-mongo.MongoDriver",
    "longname": "module:@the-/driver-mongo.MongoDriver",
    "name": "MongoDriver",
    "kind": "class",
    "scope": "static",
    "augments": [
      "Driver"
    ],
    "memberof": "module:@the-/driver-mongo",
    "meta": {
      "lineno": 1,
      "filename": "MongoDriver.js",
      "path": "/Users/okuni/Projects/the/packages/driver-mongo/lib"
    },
    "inheritdoc": "",
    "order": 2
  },
  {
    "id": "module:@the-/driver-mongo.mixins",
    "longname": "module:@the-/driver-mongo.mixins",
    "name": "mixins",
    "kind": "namespace",
    "scope": "static",
    "description": "Client mixin functions",
    "memberof": "module:@the-/driver-mongo",
    "meta": {
      "lineno": 2,
      "filename": "index.js",
      "path": "/Users/okuni/Projects/the/packages/driver-mongo/lib/mixins"
    },
    "order": 4
  },
  {
    "id": "module:@the-/driver-mongo.create",
    "longname": "module:@the-/driver-mongo.create",
    "name": "create",
    "kind": "function",
    "scope": "static",
    "description": "Create a MongoDriver instance",
    "memberof": "module:@the-/driver-mongo",
    "params": [
      {
        "type": {
          "names": [
            "*"
          ]
        },
        "variable": true,
        "name": "args"
      }
    ],
    "returns": [
      {
        "type": {
          "names": [
            "MongoDriver"
          ]
        }
      }
    ],
    "meta": {
      "lineno": 1,
      "filename": "create.js",
      "path": "/Users/okuni/Projects/the/packages/driver-mongo/lib"
    },
    "order": 0
  },
  {
    "id": "module:@the-/driver-mongo.mixins.mongoMix",
    "longname": "module:@the-/driver-mongo.mixins.mongoMix",
    "name": "mongoMix",
    "kind": "function",
    "scope": "static",
    "description": "Mixin of mongodb",
    "memberof": "module:@the-/driver-mongo.mixins",
    "meta": {
      "lineno": 1,
      "filename": "mongoMix.js",
      "path": "/Users/okuni/Projects/the/packages/driver-mongo/lib/mixins"
    },
    "order": 5
  }
]
